aggregate_profiles/__init__.py
aggregate_profiles/aggregate_profiles.py
aggregate_profiles/multiprocess.py
aggregate_profiles/read_and_write.py
aggregate_profiles/temp_testing.py
aggregate_profiles/utils.py
notebooks/test.py
tests/__init__.py
tests/test_import.py
aggregate_profiles-0.1.6.dist-info/METADATA
aggregate_profiles-0.1.6.dist-info/WHEEL
aggregate_profiles-0.1.6.dist-info/top_level.txt
aggregate_profiles-0.1.6.dist-info/RECORD
